{
  "0": {
    "user": "3ac88a6d-bbcf-4ab2-88f2-9df2e1dd32b0",
    "personalData": {
      "gender": "F",
      "zip": "07078"
    },
    "tags": {
      "POWERTOOLS": {
        "algo": "A2",
        "hist": [
          {
            "ts": {
              "$date": 1127990883540
            },
            "url": "foo/bar/baz?grimble=12&yaddayadd"
          },
          {
            "ts": {
              "$date": 469094808700
            },
            "url": "foo/bar/baz?grimble=12&yaddayadd"
          }
        ]
      },
      "PETS": {
        "algo": "A2",
        "hist": [
          {
            "ts": {
              "$date": 451578985551
            },
            "url": "foo/bar/baz?grimble=12&yaddayadd"
          },
          {
            "ts": {
              "$date": 418665508502
            },
            "url": "foo/bar/baz?grimble=12&yaddayadd"
          },
          {
            "ts": {
              "$date": 386200217276
            },
            "url": "foo/bar/baz?grimble=12&yaddayadd"
          }
        ]
      },
      "TAG1": {
        "algo": "A1",
        "hist": [
          {
            "ts": {
              "$date": 1223396976533
            },
            "url": "foo/bar/baz?grimble=12&yaddayadd"
          },
          {
            "ts": {
              "$date": 231541560922
            },
            "url": "foo/bar/baz?grimble=12&yaddayadd"
          },
          {
            "ts": {
              "$date": 421906171432
            },
            "url": "foo/bar/baz?grimble=12&yaddayadd"
          },
          {
            "ts": {
              "$date": 1377350141051
            },
            "url": "foo/bar/baz?grimble=12&yaddayadd"
          },
          {
            "ts": {
              "$date": 52519005367
            },
            "url": "foo/bar/baz?grimble=12&yaddayadd"
          },
          {
            "ts": {
              "$date": 1566568866497
            },
            "url": "foo/bar/baz?grimble=12&yaddayadd"
          },
          {
            "ts": {
              "$date": 242523376001
            },
            "url": "foo/bar/baz?grimble=12&yaddayadd"
          }
        ]
      },
      "TAG2": {
        "algo": "A4",
        "hist": [
          {
            "ts": {
              "$date": 1243302202616
            },
            "url": "foo/bar/baz?grimble=12&yaddayadd"
          },
          {
            "ts": {
              "$date": 845447025000
            },
            "url": "foo/bar/baz?grimble=12&yaddayadd"
          }
        ]
      },
      "TAG3": {
        "algo": "A1",
        "hist": [
          {
            "ts": {
              "$date": 501867867955
            },
            "url": "foo/bar/baz?grimble=12&yaddayadd"
          },
          {
            "ts": {
              "$date": 970279884191
            },
            "url": "foo/bar/baz?grimble=12&yaddayadd"
          },
          {
            "ts": {
              "$date": 554715872794
            },
            "url": "foo/bar/baz?grimble=12&yaddayadd"
          },
          {
            "ts": {
              "$date": 924928238039
            },
            "url": "foo/bar/baz?grimble=12&yaddayadd"
          },
          {
            "ts": {
              "$date": 1000993603361
            },
            "url": "foo/bar/baz?grimble=12&yaddayadd"
          },
          {
            "ts": {
              "$date": 423679772034
            },
            "url": "foo/bar/baz?grimble=12&yaddayadd"
          },
          {
            "ts": {
              "$date": 17858170894
            },
            "url": "foo/bar/baz?grimble=12&yaddayadd"
          },
          {
            "ts": {
              "$date": 730097005543
            },
            "url": "foo/bar/baz?grimble=12&yaddayadd"
          }
        ]
      },
      "TAG4": {
        "algo": "A2",
        "hist": [
          {
            "ts": {
              "$date": 626623001837
            },
            "url": "foo/bar/baz?grimble=12&yaddayadd"
          },
          {
            "ts": {
              "$date": 128662091723
            },
            "url": "foo/bar/baz?grimble=12&yaddayadd"
          },
          {
            "ts": {
              "$date": 474113072775
            },
            "url": "foo/bar/baz?grimble=12&yaddayadd"
          },
          {
            "ts": {
              "$date": 422353960024
            },
            "url": "foo/bar/baz?grimble=12&yaddayadd"
          }
        ]
      }
    }
  },
  "1": {
    "user": "6a1e9e48-0ec0-4e1a-832d-3ce007e142ef",
    "personalData": {
      "gender": "F",
      "zip": "89571"
    },
    "tags": {
      "POWERTOOLS": {
        "algo": "A1",
        "hist": [
          {
            "ts": {
              "$date": 678642797852
            },
            "url": "foo/bar/baz?grimble=12&yaddayadd"
          },
          {
            "ts": {
              "$date": 947197101394
            },
            "url": "foo/bar/baz?grimble=12&yaddayadd"
          },
          {
            "ts": {
              "$date": 272102924379
            },
            "url": "foo/bar/baz?grimble=12&yaddayadd"
          },
          {
            "ts": {
              "$date": 57725706029
            },
            "url": "foo/bar/baz?grimble=12&yaddayadd"
          }
        ]
      },
      "PETS": {
        "algo": "A1",
        "hist": [
          {
            "ts": {
              "$date": 1020631316536
            },
            "url": "foo/bar/baz?grimble=12&yaddayadd"
          },
          {
            "ts": {
              "$date": 699924643542
            },
            "url": "foo/bar/baz?grimble=12&yaddayadd"
          },
          {
            "ts": {
              "$date": 751716009468
            },
            "url": "foo/bar/baz?grimble=12&yaddayadd"
          },
          {
            "ts": {
              "$date": 229994595225
            },
            "url": "foo/bar/baz?grimble=12&yaddayadd"
          },
          {
            "ts": {
              "$date": 1040208068911
            },
            "url": "foo/bar/baz?grimble=12&yaddayadd"
          },
          {
            "ts": {
              "$date": 656676335430
            },
            "url": "foo/bar/baz?grimble=12&yaddayadd"
          }
        ]
      },
      "TAG1": {
        "algo": "A1",
        "hist": [
          {
            "ts": {
              "$date": 1276685010096
            },
            "url": "foo/bar/baz?grimble=12&yaddayadd"
          }
        ]
      },
      "TAG2": {
        "algo": "A2",
        "hist": [
          {
            "ts": {
              "$date": 1182181256931
            },
            "url": "foo/bar/baz?grimble=12&yaddayadd"
          },
          {
            "ts": {
              "$date": 405041950368
            },
            "url": "foo/bar/baz?grimble=12&yaddayadd"
          },
          {
            "ts": {
              "$date": 87493210371
            },
            "url": "foo/bar/baz?grimble=12&yaddayadd"
          },
          {
            "ts": {
              "$date": 1656411683851
            },
            "url": "foo/bar/baz?grimble=12&yaddayadd"
          },
          {
            "ts": {
              "$date": 457862905296
            },
            "url": "foo/bar/baz?grimble=12&yaddayadd"
          }
        ]
      },
      "TAG3": {
        "algo": "A2",
        "hist": [
          {
            "ts": {
              "$date": 388474055763
            },
            "url": "foo/bar/baz?grimble=12&yaddayadd"
          },
          {
            "ts": {
              "$date": 101017728997
            },
            "url": "foo/bar/baz?grimble=12&yaddayadd"
          },
          {
            "ts": {
              "$date": 1077745821772
            },
            "url": "foo/bar/baz?grimble=12&yaddayadd"
          },
          {
            "ts": {
              "$date": 273147761809
            },
            "url": "foo/bar/baz?grimble=12&yaddayadd"
          },
          {
            "ts": {
              "$date": 997566935555
            },
            "url": "foo/bar/baz?grimble=12&yaddayadd"
          },
          {
            "ts": {
              "$date": 487967585396
            },
            "url": "foo/bar/baz?grimble=12&yaddayadd"
          },
          {
            "ts": {
              "$date": 1347466457546
            },
            "url": "foo/bar/baz?grimble=12&yaddayadd"
          }
        ]
      },
      "TAG4": {
        "algo": "A2",
        "hist": [
          {
            "ts": {
              "$date": 1480280489702
            },
            "url": "foo/bar/baz?grimble=12&yaddayadd"
          },
          {
            "ts": {
              "$date": 1662331190796
            },
            "url": "foo/bar/baz?grimble=12&yaddayadd"
          },
          {
            "ts": {
              "$date": 89666046255
            },
            "url": "foo/bar/baz?grimble=12&yaddayadd"
          },
          {
            "ts": {
              "$date": 1012088976438
            },
            "url": "foo/bar/baz?grimble=12&yaddayadd"
          },
          {
            "ts": {
              "$date": 27199051102
            },
            "url": "foo/bar/baz?grimble=12&yaddayadd"
          }
        ]
      }
    }
  },
  "2": {
    "user": "faf1e703-59e5-4e4e-a107-f6f6557dd14c",
    "personalData": {
      "gender": "F",
      "zip": "89571"
    },
    "tags": {
      "POWERTOOLS": {
        "algo": "A2",
        "hist": [
          {
            "ts": {
              "$date": 1457269783291
            },
            "url": "foo/bar/baz?grimble=12&yaddayadd"
          },
          {
            "ts": {
              "$date": 74482290777
            },
            "url": "foo/bar/baz?grimble=12&yaddayadd"
          },
          {
            "ts": {
              "$date": 33179330323
            },
            "url": "foo/bar/baz?grimble=12&yaddayadd"
          }
        ]
      },
      "PETS": {
        "algo": "A1",
        "hist": [
          {
            "ts": {
              "$date": 1544118391601
            },
            "url": "foo/bar/baz?grimble=12&yaddayadd"
          },
          {
            "ts": {
              "$date": 1195341988981
            },
            "url": "foo/bar/baz?grimble=12&yaddayadd"
          },
          {
            "ts": {
              "$date": 698269678599
            },
            "url": "foo/bar/baz?grimble=12&yaddayadd"
          },
          {
            "ts": {
              "$date": 1495040130843
            },
            "url": "foo/bar/baz?grimble=12&yaddayadd"
          }
        ]
      },
      "TAG1": {
        "algo": "A4",
        "hist": [
          {
            "ts": {
              "$date": 1280996603027
            },
            "url": "foo/bar/baz?grimble=12&yaddayadd"
          },
          {
            "ts": {
              "$date": 221596409166
            },
            "url": "foo/bar/baz?grimble=12&yaddayadd"
          }
        ]
      },
      "TAG2": {
        "algo": "A2",
        "hist": [
          {
            "ts": {
              "$date": 323126879963
            },
            "url": "foo/bar/baz?grimble=12&yaddayadd"
          },
          {
            "ts": {
              "$date": 1587204541445
            },
            "url": "foo/bar/baz?grimble=12&yaddayadd"
          },
          {
            "ts": {
              "$date": 1515695941236
            },
            "url": "foo/bar/baz?grimble=12&yaddayadd"
          },
          {
            "ts": {
              "$date": 597153656356
            },
            "url": "foo/bar/baz?grimble=12&yaddayadd"
          },
          {
            "ts": {
              "$date": 1598594715203
            },
            "url": "foo/bar/baz?grimble=12&yaddayadd"
          }
        ]
      },
      "TAG3": {
        "algo": "A4",
        "hist": [
          {
            "ts": {
              "$date": 635796201511
            },
            "url": "foo/bar/baz?grimble=12&yaddayadd"
          },
          {
            "ts": {
              "$date": 1328913667941
            },
            "url": "foo/bar/baz?grimble=12&yaddayadd"
          },
          {
            "ts": {
              "$date": 247368670695
            },
            "url": "foo/bar/baz?grimble=12&yaddayadd"
          }
        ]
      },
      "TAG4": {
        "algo": "A4",
        "hist": [
          {
            "ts": {
              "$date": 1575297076401
            },
            "url": "foo/bar/baz?grimble=12&yaddayadd"
          },
          {
            "ts": {
              "$date": 346223558576
            },
            "url": "foo/bar/baz?grimble=12&yaddayadd"
          },
          {
            "ts": {
              "$date": 1133659380826
            },
            "url": "foo/bar/baz?grimble=12&yaddayadd"
          },
          {
            "ts": {
              "$date": 338346627690
            },
            "url": "foo/bar/baz?grimble=12&yaddayadd"
          }
        ]
      }
    }
  },
  "3": {
    "user": "3a52a102-7a64-4e90-b402-3e92fb70b8ca",
    "personalData": {
      "gender": "M",
      "zip": "89571"
    },
    "tags": {
      "POWERTOOLS": {
        "algo": "A4",
        "hist": [
          {
            "ts": {
              "$date": 723724146749
            },
            "url": "foo/bar/baz?grimble=12&yaddayadd"
          },
          {
            "ts": {
              "$date": 742924849174
            },
            "url": "foo/bar/baz?grimble=12&yaddayadd"
          },
          {
            "ts": {
              "$date": 763657966343
            },
            "url": "foo/bar/baz?grimble=12&yaddayadd"
          }
        ]
      },
      "PETS": {
        "algo": "A1",
        "hist": [
          {
            "ts": {
              "$date": 247854447204
            },
            "url": "foo/bar/baz?grimble=12&yaddayadd"
          }
        ]
      },
      "TAG1": {
        "algo": "A1",
        "hist": [
          {
            "ts": {
              "$date": 175581776026
            },
            "url": "foo/bar/baz?grimble=12&yaddayadd"
          },
          {
            "ts": {
              "$date": 661599149424
            },
            "url": "foo/bar/baz?grimble=12&yaddayadd"
          },
          {
            "ts": {
              "$date": 1056565824898
            },
            "url": "foo/bar/baz?grimble=12&yaddayadd"
          },
          {
            "ts": {
              "$date": 1392123330983
            },
            "url": "foo/bar/baz?grimble=12&yaddayadd"
          }
        ]
      },
      "TAG2": {
        "algo": "A2",
        "hist": [
          {
            "ts": {
              "$date": 943393879022
            },
            "url": "foo/bar/baz?grimble=12&yaddayadd"
          },
          {
            "ts": {
              "$date": 1341914646854
            },
            "url": "foo/bar/baz?grimble=12&yaddayadd"
          },
          {
            "ts": {
              "$date": 1197617466372
            },
            "url": "foo/bar/baz?grimble=12&yaddayadd"
          },
          {
            "ts": {
              "$date": 1139121572273
            },
            "url": "foo/bar/baz?grimble=12&yaddayadd"
          },
          {
            "ts": {
              "$date": 559511980658
            },
            "url": "foo/bar/baz?grimble=12&yaddayadd"
          },
          {
            "ts": {
              "$date": 485864420832
            },
            "url": "foo/bar/baz?grimble=12&yaddayadd"
          },
          {
            "ts": {
              "$date": 1180565751958
            },
            "url": "foo/bar/baz?grimble=12&yaddayadd"
          },
          {
            "ts": {
              "$date": 298514187007
            },
            "url": "foo/bar/baz?grimble=12&yaddayadd"
          }
        ]
      },
      "TAG3": {
        "algo": "A1",
        "hist": [
          {
            "ts": {
              "$date": 680880685283
            },
            "url": "foo/bar/baz?grimble=12&yaddayadd"
          },
          {
            "ts": {
              "$date": 352705319368
            },
            "url": "foo/bar/baz?grimble=12&yaddayadd"
          },
          {
            "ts": {
              "$date": 767290944489
            },
            "url": "foo/bar/baz?grimble=12&yaddayadd"
          }
        ]
      },
      "TAG4": {
        "algo": "A1",
        "hist": [
          {
            "ts": {
              "$date": 183570395578
            },
            "url": "foo/bar/baz?grimble=12&yaddayadd"
          },
          {
            "ts": {
              "$date": 1116058248868
            },
            "url": "foo/bar/baz?grimble=12&yaddayadd"
          },
          {
            "ts": {
              "$date": 1425395936485
            },
            "url": "foo/bar/baz?grimble=12&yaddayadd"
          },
          {
            "ts": {
              "$date": 1582658287811
            },
            "url": "foo/bar/baz?grimble=12&yaddayadd"
          },
          {
            "ts": {
              "$date": 960558397657
            },
            "url": "foo/bar/baz?grimble=12&yaddayadd"
          },
          {
            "ts": {
              "$date": 1177509199884
            },
            "url": "foo/bar/baz?grimble=12&yaddayadd"
          },
          {
            "ts": {
              "$date": 1407831508657
            },
            "url": "foo/bar/baz?grimble=12&yaddayadd"
          }
        ]
      }
    }
  },
  "4": {
    "user": "269bb077-75c5-46ef-ac8e-796caaee79d2",
    "personalData": {
      "gender": "F",
      "zip": "10024"
    },
    "tags": {
      "POWERTOOLS": {
        "algo": "A2",
        "hist": [
          {
            "ts": {
              "$date": 717247135258
            },
            "url": "foo/bar/baz?grimble=12&yaddayadd"
          },
          {
            "ts": {
              "$date": 1367377864397
            },
            "url": "foo/bar/baz?grimble=12&yaddayadd"
          }
        ]
      },
      "PETS": {
        "algo": "A4",
        "hist": [
          {
            "ts": {
              "$date": 1142611485013
            },
            "url": "foo/bar/baz?grimble=12&yaddayadd"
          },
          {
            "ts": {
              "$date": 1365210672684
            },
            "url": "foo/bar/baz?grimble=12&yaddayadd"
          },
          {
            "ts": {
              "$date": 588921324322
            },
            "url": "foo/bar/baz?grimble=12&yaddayadd"
          }
        ]
      },
      "TAG1": {
        "algo": "A2",
        "hist": [
          {
            "ts": {
              "$date": 726274832988
            },
            "url": "foo/bar/baz?grimble=12&yaddayadd"
          },
          {
            "ts": {
              "$date": 702701264882
            },
            "url": "foo/bar/baz?grimble=12&yaddayadd"
          },
          {
            "ts": {
              "$date": 1547808722616
            },
            "url": "foo/bar/baz?grimble=12&yaddayadd"
          },
          {
            "ts": {
              "$date": 1551227158464
            },
            "url": "foo/bar/baz?grimble=12&yaddayadd"
          },
          {
            "ts": {
              "$date": 901641252861
            },
            "url": "foo/bar/baz?grimble=12&yaddayadd"
          },
          {
            "ts": {
              "$date": 1412410156061
            },
            "url": "foo/bar/baz?grimble=12&yaddayadd"
          }
        ]
      },
      "TAG2": {
        "algo": "A2",
        "hist": [
          {
            "ts": {
              "$date": 1203938865464
            },
            "url": "foo/bar/baz?grimble=12&yaddayadd"
          },
          {
            "ts": {
              "$date": 1512442373630
            },
            "url": "foo/bar/baz?grimble=12&yaddayadd"
          },
          {
            "ts": {
              "$date": 1129387216290
            },
            "url": "foo/bar/baz?grimble=12&yaddayadd"
          }
        ]
      },
      "TAG3": {
        "algo": "A2",
        "hist": [
          {
            "ts": {
              "$date": 31166124632
            },
            "url": "foo/bar/baz?grimble=12&yaddayadd"
          },
          {
            "ts": {
              "$date": 1308164754046
            },
            "url": "foo/bar/baz?grimble=12&yaddayadd"
          },
          {
            "ts": {
              "$date": 557566448809
            },
            "url": "foo/bar/baz?grimble=12&yaddayadd"
          },
          {
            "ts": {
              "$date": 907787608551
            },
            "url": "foo/bar/baz?grimble=12&yaddayadd"
          },
          {
            "ts": {
              "$date": 520773612028
            },
            "url": "foo/bar/baz?grimble=12&yaddayadd"
          },
          {
            "ts": {
              "$date": 1567149238694
            },
            "url": "foo/bar/baz?grimble=12&yaddayadd"
          }
        ]
      },
      "TAG4": {
        "algo": "A1",
        "hist": [
          {
            "ts": {
              "$date": 465536117818
            },
            "url": "foo/bar/baz?grimble=12&yaddayadd"
          },
          {
            "ts": {
              "$date": 674314011197
            },
            "url": "foo/bar/baz?grimble=12&yaddayadd"
          },
          {
            "ts": {
              "$date": 1574203125730
            },
            "url": "foo/bar/baz?grimble=12&yaddayadd"
          },
          {
            "ts": {
              "$date": 58573030863
            },
            "url": "foo/bar/baz?grimble=12&yaddayadd"
          },
          {
            "ts": {
              "$date": 1195721484785
            },
            "url": "foo/bar/baz?grimble=12&yaddayadd"
          },
          {
            "ts": {
              "$date": 1035523276633
            },
            "url": "foo/bar/baz?grimble=12&yaddayadd"
          },
          {
            "ts": {
              "$date": 1272115276762
            },
            "url": "foo/bar/baz?grimble=12&yaddayadd"
          }
        ]
      }
    }
  },
  "5": {
    "user": "f3f2aa42-e91f-4434-85e4-3c436b737757",
    "personalData": {
      "gender": "F",
      "zip": "10001"
    },
    "tags": {
      "POWERTOOLS": {
        "algo": "A1",
        "hist": [
          {
            "ts": {
              "$date": 646356757222
            },
            "url": "foo/bar/baz?grimble=12&yaddayadd"
          },
          {
            "ts": {
              "$date": 178639316481
            },
            "url": "foo/bar/baz?grimble=12&yaddayadd"
          },
          {
            "ts": {
              "$date": 1228872183266
            },
            "url": "foo/bar/baz?grimble=12&yaddayadd"
          },
          {
            "ts": {
              "$date": 837429758832
            },
            "url": "foo/bar/baz?grimble=12&yaddayadd"
          }
        ]
      },
      "PETS": {
        "algo": "A2",
        "hist": [
          {
            "ts": {
              "$date": 714273226175
            },
            "url": "foo/bar/baz?grimble=12&yaddayadd"
          },
          {
            "ts": {
              "$date": 343318065387
            },
            "url": "foo/bar/baz?grimble=12&yaddayadd"
          },
          {
            "ts": {
              "$date": 1217429969375
            },
            "url": "foo/bar/baz?grimble=12&yaddayadd"
          }
        ]
      },
      "TAG1": {
        "algo": "A1",
        "hist": [
          {
            "ts": {
              "$date": 1243515818139
            },
            "url": "foo/bar/baz?grimble=12&yaddayadd"
          },
          {
            "ts": {
              "$date": 742911540786
            },
            "url": "foo/bar/baz?grimble=12&yaddayadd"
          }
        ]
      },
      "TAG2": {
        "algo": "A2",
        "hist": [
          {
            "ts": {
              "$date": 1499033755680
            },
            "url": "foo/bar/baz?grimble=12&yaddayadd"
          },
          {
            "ts": {
              "$date": 29170279474
            },
            "url": "foo/bar/baz?grimble=12&yaddayadd"
          },
          {
            "ts": {
              "$date": 1185017104556
            },
            "url": "foo/bar/baz?grimble=12&yaddayadd"
          },
          {
            "ts": {
              "$date": 750558083088
            },
            "url": "foo/bar/baz?grimble=12&yaddayadd"
          },
          {
            "ts": {
              "$date": 564761184460
            },
            "url": "foo/bar/baz?grimble=12&yaddayadd"
          },
          {
            "ts": {
              "$date": 1144548291346
            },
            "url": "foo/bar/baz?grimble=12&yaddayadd"
          }
        ]
      },
      "TAG3": {
        "algo": "A4",
        "hist": [
          {
            "ts": {
              "$date": 737880663177
            },
            "url": "foo/bar/baz?grimble=12&yaddayadd"
          },
          {
            "ts": {
              "$date": 1119356877027
            },
            "url": "foo/bar/baz?grimble=12&yaddayadd"
          },
          {
            "ts": {
              "$date": 1174426476614
            },
            "url": "foo/bar/baz?grimble=12&yaddayadd"
          },
          {
            "ts": {
              "$date": 1315103078122
            },
            "url": "foo/bar/baz?grimble=12&yaddayadd"
          },
          {
            "ts": {
              "$date": 76603279956
            },
            "url": "foo/bar/baz?grimble=12&yaddayadd"
          },
          {
            "ts": {
              "$date": 1113898426214
            },
            "url": "foo/bar/baz?grimble=12&yaddayadd"
          },
          {
            "ts": {
              "$date": 1424903495646
            },
            "url": "foo/bar/baz?grimble=12&yaddayadd"
          },
          {
            "ts": {
              "$date": 1021906143919
            },
            "url": "foo/bar/baz?grimble=12&yaddayadd"
          }
        ]
      },
      "TAG4": {
        "algo": "A2",
        "hist": [
          {
            "ts": {
              "$date": 899454812196
            },
            "url": "foo/bar/baz?grimble=12&yaddayadd"
          },
          {
            "ts": {
              "$date": 786253841583
            },
            "url": "foo/bar/baz?grimble=12&yaddayadd"
          },
          {
            "ts": {
              "$date": 167280232915
            },
            "url": "foo/bar/baz?grimble=12&yaddayadd"
          },
          {
            "ts": {
              "$date": 95076470973
            },
            "url": "foo/bar/baz?grimble=12&yaddayadd"
          },
          {
            "ts": {
              "$date": 439983173945
            },
            "url": "foo/bar/baz?grimble=12&yaddayadd"
          },
          {
            "ts": {
              "$date": 959376547952
            },
            "url": "foo/bar/baz?grimble=12&yaddayadd"
          }
        ]
      }
    }
  },
  "6": {
    "user": "2787356a-c4e2-4c95-b0ba-2ff253a02bf9",
    "personalData": {
      "gender": "F",
      "zip": "89571"
    },
    "tags": {
      "POWERTOOLS": {
        "algo": "A4",
        "hist": [
          {
            "ts": {
              "$date": 630552471516
            },
            "url": "foo/bar/baz?grimble=12&yaddayadd"
          },
          {
            "ts": {
              "$date": 432554601007
            },
            "url": "foo/bar/baz?grimble=12&yaddayadd"
          },
          {
            "ts": {
              "$date": 806226995364
            },
            "url": "foo/bar/baz?grimble=12&yaddayadd"
          },
          {
            "ts": {
              "$date": 1002925031209
            },
            "url": "foo/bar/baz?grimble=12&yaddayadd"
          }
        ]
      },
      "PETS": {
        "algo": "A1",
        "hist": [
          {
            "ts": {
              "$date": 319327143563
            },
            "url": "foo/bar/baz?grimble=12&yaddayadd"
          }
        ]
      },
      "TAG1": {
        "algo": "A2",
        "hist": [
          {
            "ts": {
              "$date": 665576207291
            },
            "url": "foo/bar/baz?grimble=12&yaddayadd"
          },
          {
            "ts": {
              "$date": 32460345765
            },
            "url": "foo/bar/baz?grimble=12&yaddayadd"
          }
        ]
      },
      "TAG2": {
        "algo": "A2",
        "hist": [
          {
            "ts": {
              "$date": 1650911973935
            },
            "url": "foo/bar/baz?grimble=12&yaddayadd"
          },
          {
            "ts": {
              "$date": 1640367162627
            },
            "url": "foo/bar/baz?grimble=12&yaddayadd"
          },
          {
            "ts": {
              "$date": 53406990406
            },
            "url": "foo/bar/baz?grimble=12&yaddayadd"
          },
          {
            "ts": {
              "$date": 209879792095
            },
            "url": "foo/bar/baz?grimble=12&yaddayadd"
          },
          {
            "ts": {
              "$date": 270949841359
            },
            "url": "foo/bar/baz?grimble=12&yaddayadd"
          },
          {
            "ts": {
              "$date": 718192077012
            },
            "url": "foo/bar/baz?grimble=12&yaddayadd"
          }
        ]
      },
      "TAG3": {
        "algo": "A4",
        "hist": [
          {
            "ts": {
              "$date": 470024099667
            },
            "url": "foo/bar/baz?grimble=12&yaddayadd"
          },
          {
            "ts": {
              "$date": 303328238073
            },
            "url": "foo/bar/baz?grimble=12&yaddayadd"
          },
          {
            "ts": {
              "$date": 841030482489
            },
            "url": "foo/bar/baz?grimble=12&yaddayadd"
          }
        ]
      },
      "TAG4": {
        "algo": "A1",
        "hist": [
          {
            "ts": {
              "$date": 237549393776
            },
            "url": "foo/bar/baz?grimble=12&yaddayadd"
          },
          {
            "ts": {
              "$date": 1121438174695
            },
            "url": "foo/bar/baz?grimble=12&yaddayadd"
          },
          {
            "ts": {
              "$date": 316651004806
            },
            "url": "foo/bar/baz?grimble=12&yaddayadd"
          },
          {
            "ts": {
              "$date": 559183142293
            },
            "url": "foo/bar/baz?grimble=12&yaddayadd"
          }
        ]
      }
    }
  },
  "7": {
    "user": "2224551d-d272-4f37-b09a-7950f744e680",
    "personalData": {
      "gender": "F",
      "zip": "07078"
    },
    "tags": {
      "POWERTOOLS": {
        "algo": "A2",
        "hist": [
          {
            "ts": {
              "$date": 107128611389
            },
            "url": "foo/bar/baz?grimble=12&yaddayadd"
          },
          {
            "ts": {
              "$date": 1644787047813
            },
            "url": "foo/bar/baz?grimble=12&yaddayadd"
          },
          {
            "ts": {
              "$date": 303167185215
            },
            "url": "foo/bar/baz?grimble=12&yaddayadd"
          }
        ]
      },
      "PETS": {
        "algo": "A4",
        "hist": [
          {
            "ts": {
              "$date": 655059480041
            },
            "url": "foo/bar/baz?grimble=12&yaddayadd"
          },
          {
            "ts": {
              "$date": 156913046969
            },
            "url": "foo/bar/baz?grimble=12&yaddayadd"
          },
          {
            "ts": {
              "$date": 1627744689324
            },
            "url": "foo/bar/baz?grimble=12&yaddayadd"
          },
          {
            "ts": {
              "$date": 1426502147639
            },
            "url": "foo/bar/baz?grimble=12&yaddayadd"
          },
          {
            "ts": {
              "$date": 23196916545
            },
            "url": "foo/bar/baz?grimble=12&yaddayadd"
          },
          {
            "ts": {
              "$date": 900152334237
            },
            "url": "foo/bar/baz?grimble=12&yaddayadd"
          },
          {
            "ts": {
              "$date": 1336217303543
            },
            "url": "foo/bar/baz?grimble=12&yaddayadd"
          },
          {
            "ts": {
              "$date": 236679752965
            },
            "url": "foo/bar/baz?grimble=12&yaddayadd"
          }
        ]
      },
      "TAG1": {
        "algo": "A2",
        "hist": [
          {
            "ts": {
              "$date": 110691444886
            },
            "url": "foo/bar/baz?grimble=12&yaddayadd"
          },
          {
            "ts": {
              "$date": 1238212479674
            },
            "url": "foo/bar/baz?grimble=12&yaddayadd"
          }
        ]
      },
      "TAG2": {
        "algo": "A4",
        "hist": [
          {
            "ts": {
              "$date": 955716482850
            },
            "url": "foo/bar/baz?grimble=12&yaddayadd"
          },
          {
            "ts": {
              "$date": 586100975985
            },
            "url": "foo/bar/baz?grimble=12&yaddayadd"
          },
          {
            "ts": {
              "$date": 797719023710
            },
            "url": "foo/bar/baz?grimble=12&yaddayadd"
          },
          {
            "ts": {
              "$date": 1521491816235
            },
            "url": "foo/bar/baz?grimble=12&yaddayadd"
          },
          {
            "ts": {
              "$date": 915148345222
            },
            "url": "foo/bar/baz?grimble=12&yaddayadd"
          },
          {
            "ts": {
              "$date": 924153120219
            },
            "url": "foo/bar/baz?grimble=12&yaddayadd"
          }
        ]
      },
      "TAG3": {
        "algo": "A4",
        "hist": [
          {
            "ts": {
              "$date": 231610842758
            },
            "url": "foo/bar/baz?grimble=12&yaddayadd"
          },
          {
            "ts": {
              "$date": 160539858886
            },
            "url": "foo/bar/baz?grimble=12&yaddayadd"
          },
          {
            "ts": {
              "$date": 815593372760
            },
            "url": "foo/bar/baz?grimble=12&yaddayadd"
          },
          {
            "ts": {
              "$date": 1476728645150
            },
            "url": "foo/bar/baz?grimble=12&yaddayadd"
          }
        ]
      },
      "TAG4": {
        "algo": "A2",
        "hist": [
          {
            "ts": {
              "$date": 1410776847325
            },
            "url": "foo/bar/baz?grimble=12&yaddayadd"
          },
          {
            "ts": {
              "$date": 82096831656
            },
            "url": "foo/bar/baz?grimble=12&yaddayadd"
          },
          {
            "ts": {
              "$date": 1034330534824
            },
            "url": "foo/bar/baz?grimble=12&yaddayadd"
          },
          {
            "ts": {
              "$date": 441757210515
            },
            "url": "foo/bar/baz?grimble=12&yaddayadd"
          },
          {
            "ts": {
              "$date": 1276630315029
            },
            "url": "foo/bar/baz?grimble=12&yaddayadd"
          },
          {
            "ts": {
              "$date": 1538024543013
            },
            "url": "foo/bar/baz?grimble=12&yaddayadd"
          },
          {
            "ts": {
              "$date": 1585074601731
            },
            "url": "foo/bar/baz?grimble=12&yaddayadd"
          },
          {
            "ts": {
              "$date": 706105248646
            },
            "url": "foo/bar/baz?grimble=12&yaddayadd"
          }
        ]
      }
    }
  }
}